{
  "message_id": "19a556aaddd72418",
  "chunked_at": "2025-12-08T14:28:35.972751",
  "total_chunks": 1,
  "chunks": [
    {
      "chunk_id": "19a556aaddd72418_email_0_f6b62a3a",
      "text": "Hi Ankita, This is a reminder about the following upcoming bookings: Space Information Location: Bobst Library I need a space for: Silent Study Space: Floor 4 Graduate Individual Study Room 419 Date: Wednesday, November 5, 2025 Time: 3:15pm - 5:00pm Directions: Floor 4 Graduate Individual Study Room 419 : Floor 4 South To cancel this booking visit: https://nyu.libcal.com/equipment/cancel?id=e207ce4821d4 Powered by Springshare. Read our privacy policy .",
      "metadata": {
        "chunk_index": 0,
        "source_type": "email_body",
        "message_id": "19a556aaddd72418",
        "from": "LibCal <alerts@mail.libcal.com>",
        "to": [],
        "subject": "Reminder about your upcoming booking at Bobst Library",
        "date": "Wed, 05 Nov 2025 19:07:22 +0000",
        "timestamp": 1762369642,
        "token_count": 114
      }
    }
  ]
}