{
  "message_id": "19a5fc95556c2c69",
  "chunked_at": "2025-12-08T14:29:39.364187",
  "total_chunks": 1,
  "chunks": [
    {
      "chunk_id": "19a5fc95556c2c69_email_0_76152753",
      "text": "Handshake Maggie just messaged you about a job Hello! My name is Maggie, and I am a Manager at iD Tech ( https://www.idtech.com/ ) . Are you looking for a job around New York City  this summer? We are looking for Instructors ( https://www.idtech ... Read more View message Mute iD Tech Hiring Stem Instructors · You received this email because Handshake partners with your school to help you grow your career. Manage email preferences or unsubscribe . P.O. Box 40770, San Francisco, CA 94140",
      "metadata": {
        "chunk_index": 0,
        "source_type": "email_body",
        "message_id": "19a5fc95556c2c69",
        "from": "Maggie Wright via Handshake <handshake@notifications.joinhandshake.com>",
        "to": [],
        "subject": "Hiring Stem Instructors in New York",
        "date": "Fri, 07 Nov 2025 19:27:00 +0000",
        "timestamp": 1762543620,
        "token_count": 122
      }
    }
  ]
}