{
  "id": "19a809c1cc769d53",
  "from": "Handshake <handshake@notifications.joinhandshake.com>",
  "subject": "Weekly digest: 2 unread messages are waiting for you ",
  "date": "Fri, 14 Nov 2025 04:25:03 +0000",
  "eml_path": "data/raw_emails/19a809c1cc769d53.eml",
  "attachments": [],
  "body_text": "2 unread messages since last Thursday\r\n\r\n\r\n1 employer: iD Tech\r\n1 job in: Education\r\n\r\n\r\n\r\n\r\n\r\n\r\n\r\n\r\n\r\n\r\n\r\n\r\n\r\n\r\n\r\n\r\n\r\nMaggie Wright\r\n\r\n\r\n\r\n\r\niD Tech 路 Regional Manager\r\n\r\n\r\n\r\n\r\n\r\n\r\n\r\n\r\nAdministrative Aide\r\n\r\n\r\n\r\n\r\n\r\n\r\n\r\n\r\n\r\nOnsite\r\n\r\n\r\n\r\nJob\r\n\r\n\r\n\r\n\r\n\r\n\r\n\r\n\r\n\r\n\r\n\r\n\r\n\r\n\r\n\r\n\r\n\r\n\r\n\r\n\r\n\r\n\r\n\r\n\r\n\r\n\r\n\r\n\r\n\r\n\r\n\r\nMaggie Wright\r\n\r\n\r\n\r\n\r\niD Tech 路 Regional Manager\r\n\r\n\r\n\r\n\r\n\r\n\r\n\r\n\r\nAdministrative Aide\r\n\r\n\r\n\r\n\r\n\r\n\r\n\r\n\r\n\r\nOnsite\r\n\r\n\r\n\r\nJob\r\n\r\n\r\n\r\n\r\n\r\n\r\n\r\n\r\n\r\n\r\n\r\n\r\n\r\n\r\n\r\n\r\n\r\n\r\n\r\n\r\nCatch up on messages\r\n\r\n\r\n\r\n\r\n\r\n\r\n\r\nWant daily digests? Update your preferences.",
  "body_html": "<!DOCTYPE html>\r\n<html xmlns=\"http://www.w3.org/1999/xhtml\" style=\"min-height:100%;background:#f5f5f5;background-color:transparent\">\r\n<head>\r\n<meta content=\"text/html; charset=utf-8\" http-equiv=\"Content-Type\">\r\n<meta content=\"width=device-width\" name=\"viewport\">\r\n<title>Handshake</title>\r\n\r\n\r\n\r\n\r\n\r\n\r\n\r\n<style>@media only screen and (max-width: 664px) {\r\n.small-float-center{margin:0 auto !important;float:none !important;text-align:center !important}\r\n.small-text-center{text-align:center !important}\r\n.small-text-left{text-align:left !important}\r\n.small-text-right{text-align:right !important}\r\n.hide-for-large{display:block !important;width:auto !important;overflow:visible !important;max-height:none !important;font-size:inherit !important;line-height:inherit !important}\r\ntable.body table.container .hide-for-large{display:table !important;width:100% !important}\r\ntable.body table.container .row.hide-for-large{display:table !important;width:100% !important}\r\ntable.body table.container .callout-inner.hide-for-large{display:table-cell !important;width:100% !important}\r\ntable.body table.container .show-for-large{display:none !important;width:0;mso-hide:all;overflow:hidden}\r\ntable.body img{width:auto;height:auto}\r\ntable.body center{min-width:0 !important}\r\ntable.body .container{width:95% !important}\r\ntable.body .columns{height:auto !important;-moz-box-sizing:border-box;-webkit-box-sizing:border-box;box-sizing:border-box;padding-left:64px !important;padding-right:64px !important}\r\ntable.body .column{height:auto !important;-moz-box-sizing:border-box;-webkit-box-sizing:border-box;box-sizing:border-box;padding-left:64px !important;padding-right:64px !important}\r\ntable.body .columns .column{padding-left:0 !important;padding-right:0 !important}\r\ntable.body .columns .columns{padding-left:0 !important;padding-right:0 !important}\r\ntable.body .column .column{padding-left:0 !important;padding-right:0 !important}\r\ntable.body .column .columns{padding-left:0 !important;padding-right:0 !important}\r\ntable.body .collapse .columns{padding-left:0 !important;padding-right:0 !important}\r\ntable.body .collapse .column{padding-left:0 !important;padding-right:0 !important}\r\ntd.small-1{display:inline-block !important;width:8.33333% !important}\r\nth.small-1{display:inline-block !important;width:8.33333% !important}\r\ntd.small-2{display:inline-block !important;width:16.66667% !important}\r\nth.small-2{display:inline-block !important;width:16.66667% !important}\r\ntd.small-3{display:inline-block !important;width:25% !important}\r\nth.small-3{display:inline-block !important;width:25% !important}\r\ntd.small-4{display:inline-block !important;width:33.33333% !important}\r\nth.small-4{display:inline-block !important;width:33.33333% !important}\r\ntd.small-5{display:inline-block !important;width:41.66667% !important}\r\nth.small-5{display:inline-block !important;width:41.66667% !important}\r\ntd.small-6{display:inline-block !important;width:50% !important}\r\nth.small-6{display:inline-block !important;width:50% !important}\r\ntd.small-7{display:inline-block !important;width:58.33333% !important}\r\nth.small-7{display:inline-block !important;width:58.33333% !important}\r\ntd.small-8{display:inline-block !important;width:66.66667% !important}\r\nth.small-8{display:inline-block !important;width:66.66667% !important}\r\ntd.small-9{display:inline-block !important;width:75% !important}\r\nth.small-9{display:inline-block !important;width:75% !important}\r\ntd.small-10{display:inline-block !important;width:83.33333% !important}\r\nth.small-10{display:inline-block !important;width:83.33333% !important}\r\ntd.small-11{display:inline-block !important;width:91.66667% !important}\r\nth.small-11{display:inline-block !important;width:91.66667% !important}\r\ntd.small-12{display:inline-block !important;width:100% !important}\r\nth.small-12{display:inline-block !important;width:100% !important}\r\n.columns td.small-12{display:block !important;width:100% !important}\r\n.column td.small-12{display:block !important;width:100% !important}\r\n.columns th.small-12{display:block !important;width:100% !important}\r\n.column th.small-12{display:block !important;width:100% !important}\r\ntable.body td.small-offset-1{margin-left:8.33333% !important}\r\ntable.body th.small-offset-1{margin-left:8.33333% !important}\r\ntable.body td.small-offset-2{margin-left:16.66667% !important}\r\ntable.body th.small-offset-2{margin-left:16.66667% !important}\r\ntable.body td.small-offset-3{margin-left:25% !important}\r\ntable.body th.small-offset-3{margin-left:25% !important}\r\ntable.body td.small-offset-4{margin-left:33.33333% !important}\r\ntable.body th.small-offset-4{margin-left:33.33333% !important}\r\ntable.body td.small-offset-5{margin-left:41.66667% !important}\r\ntable.body th.small-offset-5{margin-left:41.66667% !important}\r\ntable.body td.small-offset-6{margin-left:50% !important}\r\ntable.body th.small-offset-6{margin-left:50% !important}\r\ntable.body td.small-offset-7{margin-left:58.33333% !important}\r\ntable.body th.small-offset-7{margin-left:58.33333% !important}\r\ntable.body td.small-offset-8{margin-left:66.66667% !important}\r\ntable.body th.small-offset-8{margin-left:66.66667% !important}\r\ntable.body td.small-offset-9{margin-left:75% !important}\r\ntable.body th.small-offset-9{margin-left:75% !important}\r\ntable.body td.small-offset-10{margin-left:83.33333% !important}\r\ntable.body th.small-offset-10{margin-left:83.33333% !important}\r\ntable.body td.small-offset-11{margin-left:91.66667% !important}\r\ntable.body th.small-offset-11{margin-left:91.66667% !important}\r\ntable.body table.columns td.expander{display:none !important}\r\ntable.body table.columns th.expander{display:none !important}\r\ntable.body .right-text-pad{padding-left:10px !important}\r\ntable.body .text-pad-right{padding-left:10px !important}\r\ntable.body .left-text-pad{padding-right:10px !important}\r\ntable.body .text-pad-left{padding-right:10px !important}\r\ntable.menu{width:100% !important}\r\ntable.menu td{width:auto !important;display:inline-block !important}\r\ntable.menu th{width:auto !important;display:inline-block !important}\r\ntable.menu.vertical td{display:block !important}\r\ntable.menu.vertical th{display:block !important}\r\ntable.menu.small-vertical td{display:block !important}\r\ntable.menu.small-vertical th{display:block !important}\r\ntable.menu[align=\"center\"]{width:auto !important}\r\ntable.button.small-expand{width:100% !important}\r\ntable.button.small-expanded{width:100% !important}\r\ntable.button.small-expand table{width:100%}\r\ntable.button.small-expanded table{width:100%}\r\ntable.button.small-expand table a{text-align:center !important;width:100% !important;padding-left:0 !important;padding-right:0 !important}\r\ntable.button.small-expanded table a{text-align:center !important;width:100% !important;padding-left:0 !important;padding-right:0 !important}\r\ntable.button.small-expand center{min-width:0}\r\ntable.button.small-expanded center{min-width:0}\r\nth.columns.first.small-12{padding-left:16px !important}\r\nth.columns.last.small-12{padding-right:16px !important}\r\ntable.body img.icon-20{width:20px;height:20px}\r\n}\r\ntable.button:hover table tr td a{color:#ffffff}\r\ntable.button:active table tr td a{color:#ffffff}\r\ntable.button table tr td a:visited{color:#ffffff}\r\ntable.button.tiny:hover table tr td a{color:#ffffff}\r\ntable.button.tiny:active table tr td a{color:#ffffff}\r\ntable.button.tiny table tr td a:visited{color:#ffffff}\r\ntable.button.small:hover table tr td a{color:#ffffff}\r\ntable.button.small:active table tr td a{color:#ffffff}\r\ntable.button.small table tr td a:visited{color:#ffffff}\r\ntable.button.large:hover table tr td a{color:#ffffff}\r\ntable.button.large:active table tr td a{color:#ffffff}\r\ntable.button.large table tr td a:visited{color:#ffffff}\r\ntable.button:hover table td{background:#04191b;color:#ffffff}\r\ntable.button:visited table td{background:#04191b;color:#ffffff}\r\ntable.button:active table td{background:#04191b;color:#ffffff}\r\ntable.button:hover table a{border:0 solid #04191b}\r\ntable.button:visited table a{border:0 solid #04191b}\r\ntable.button:active table a{border:0 solid #04191b}\r\ntable.button.secondary:hover table td{background:#919191;color:#ffffff}\r\ntable.button.secondary:hover table a{border:0 solid #919191}\r\ntable.button.secondary:hover table td a{color:#ffffff}\r\ntable.button.secondary:active table td a{color:#ffffff}\r\ntable.button.secondary table td a:visited{color:#ffffff}\r\ntable.button.success:hover table td{background:#004d33}\r\ntable.button.success:hover table a{border:0 solid #004d33}\r\ntable.button.alert:hover table td{background:#99000d}\r\ntable.button.alert:hover table a{border:0 solid #99000d}\r\ntable.button.warning:hover table td{background:#cc8800}\r\ntable.button.warning:hover table a{border:0px solid #cc8800}\r\n.thumbnail:hover{box-shadow:0 0 6px 1px rgba(0,85,204,0.5)}\r\n.thumbnail:focus{box-shadow:0 0 6px 1px rgba(0,85,204,0.5)}\r\ntable.button.secondary:hover table td{background:#dcdcdc;border-color:#dcdcdc;color:rgba(8,8,8,0.79)}\r\ntable.button.secondary table tr td a:visited{color:rgba(8,8,8,0.79)}\r\ntable.button.secondary:hover table tr td a{color:rgba(8,8,8,0.79)}\r\ntable.button.secondary:hover table tr td a:visited{color:rgba(8,8,8,0.79)}\r\na:hover{color:#254fa5}\r\na:active{color:#183684}\r\na.plain:hover{color:#2e2a2b}\r\na.plain:active{color:#1c1819}\r\n.primary-button a:hover{color:inherit}\r\n.outline-button a:hover{color:inherit}\r\n.button a:hover{color:inherit}\r\n.primary-button a:active{color:inherit}\r\n.outline-button a:active{color:inherit}\r\n.button a:active{color:inherit}\r\n.primary-button:hover{color:#fff;background-color:#062e32;border-color:1px solid #062e32}\r\n.primary-button:active{color:#fff;background-color:#073d42;border-color:1px solid #062e32}\r\n.outline-button:hover{color:#062e32;border-color:#062e32}\r\n.outline-button:active{color:#073d42;border-color:#073d42}\r\ntable.lined a:hover{text-decoration:none}\r\n@media (max-width: 767px) {\r\n.avatar--mobile-md{max-width:56px}\r\n}\r\n@media screen and (max-width: 767px) {\r\n.padding-content{padding:0 16px !important}\r\ntable.student-footer-v3{padding:0 16px}\r\ntable.student-footer-v3 td.socials img{padding:0 12% 0 0 !important}\r\ntable.student-footer-v3 td.app-store img{padding:0 0 0 4% !important}\r\ntable.rebrand-cta{width:100% !important}\r\ntd.avatar_title{font-size:16px !important}\r\ntd.avatar_subtitle{font-size:12px !important}\r\ntd.avatar_title{font-size:16px !important}\r\ntd.avatar_subtitle{font-size:12px !important}\r\n}\r\n@media (min-width: 768px) {\r\ntd.email-footer .hiring-team-footer .media-links-container{display:flex;justify-content:space-between;margin-bottom:32px}\r\ntd.email-footer .employer-hosted-meetings-footer .media-links-container{display:flex;justify-content:space-between;margin-bottom:32px}\r\ntable.email-footer .hiring-team-footer .media-links-container{display:flex;justify-content:space-between;margin-bottom:32px}\r\ntable.email-footer .employer-hosted-meetings-footer .media-links-container{display:flex;justify-content:space-between;margin-bottom:32px}\r\n}\r\n@media screen and (max-width: 240px) {\r\n.event-card-container table.event-attendees .logo-group .event-detail .event-tags{white-space:nowrap}\r\n}</style></head>\r\n<body class=\"rebrand\" style=\"min-width:100%;-webkit-text-size-adjust:100%;-ms-text-size-adjust:100%;margin:0;padding:0;-moz-box-sizing:border-box;-webkit-box-sizing:border-box;box-sizing:border-box;font-family:&quot;Suisse Int'l&quot;, -apple-system, BlinkMacSystemFont, &quot;Segoe UI&quot;, Roboto, &quot;Helvetica Neue&quot;, sans-serif;color:#231f20;font-size:16px;line-height:20px;background-color:#f3f4fa;width:100% !important\">\r\n<table class=\"body email-layout rebrand\" data-made-with-foundation=\"\" style=\"border-spacing:0;vertical-align:top;text-align:left;background:#f5f5f5;height:100%;background-color:transparent;max-width:728px;table-layout:fixed;border:0;border-collapse:collapse;width:100%;text-align:inherit;margin:auto;padding:0;background-color:white\">\r\n<tr style=\"padding:0;vertical-align:top;text-align:left\">\r\n<td class=\"email-header\" style=\"font-family:&quot;Suisse Int'l&quot;, -apple-system, BlinkMacSystemFont, &quot;Segoe UI&quot;, Roboto, &quot;Helvetica Neue&quot;, sans-serif;padding:0;vertical-align:top;text-align:left\">\r\n<div class=\"padding-content\" style=\"padding:0 40px\">\r\n<table style=\"border-spacing:0;border-collapse:collapse;padding:0;vertical-align:top;text-align:left;width: 100%\">\r\n<tr style=\"padding:0;vertical-align:top;text-align:left\">\r\n<td style=\"font-family:&quot;Suisse Int'l&quot;, -apple-system, BlinkMacSystemFont, &quot;Segoe UI&quot;, Roboto, &quot;Helvetica Neue&quot;, sans-serif;padding:0;vertical-align:top;text-align:left\">\r\n<a href=\"https://urldefense.proofpoint.com/v2/url?u=https-3A__email.notifications.joinhandshake.com_c_eJxkkEmu2zAQRE9DbgwZnMRhwUUAx9cgOLRsxhJlcEii2wcKfoIM2-2D4C6tVLliUjFQZLleTECE44hs3n1ZW95yVH3-5FNeXE4WImhDjJii1mESxKcp6Kgmwz2RXia5qIifdmFsYUYqrqXmgarAhOaKzpSoGEBpnC0jbKaUCiLYTPg1KcGZpslEEpOaBRLkz-2D52-5FbLn8vQltad-5FwTXuG17ts-5Fd3Q-5FwTYnfE7uUY-5F6fOF7-2DPvrm2jxoB8dsoFXxyuYT9u9ugNf8Ad66Fipg8oxukPDbEbz8lfByj394-2DPwrit28Ar-5FVwKT-2DgdfyvI6WIMFHpKWojJmGYmEI0y7QwpiVfFE-2DC4Hfd04jdhRFf0O3n7b3uB9TLr5Z2QUxewlhflw-5FEhqv1XcqZnm6OcYU0cLexgu-5FgculQi19-5FD-5FqbcTSoJ9tsKJGaEvzVsh8BAAD-5F-5F-2DJOpS4&amp;d=DwMFaQ&amp;c=slrrB7dE8n7gBJbeO0g-IQ&amp;r=W4d5O1KeqHtZtS8Ifj-gIg&amp;m=Q7pIZx-6cQ6vyddP4tov8Ls2D1CYRZ5KpCVoAhq-ukTWHUhvBOSp2EGnmzkHupeZ&amp;s=uTmqNLArmbu3OSAw023N1EoNYrSjc55eEKnk9viOVT4&amp;e=\" style=\"color:#254fa5;font-weight:inherit;color: inherit; text-decoration: none;\">\r\n<img alt=\"Handshake\" class=\"handshake-logo lime\" height=\"36\" src=\"https://handshake-production-cdn.joinhandshake.com/static_assets/hs-icon-lime-round.png\" title=\"Handshake\" width=\"36\" style=\"outline:none;text-decoration:none;-ms-interpolation-mode:bicubic;width:auto;max-width:100%;clear:both;display:block;border:none;margin-top:24px;margin-bottom:16px;width:36px;height:36px;margin:24px 0\">\r\n</a>\r\n</td>\r\n</tr>\r\n</table>\r\n\r\n</div>\r\n</td>\r\n</tr>\r\n<tr style=\"padding:0;vertical-align:top;text-align:left\">\r\n<td class=\"email-content\" style=\"font-family:&quot;Suisse Int'l&quot;, -apple-system, BlinkMacSystemFont, &quot;Segoe UI&quot;, Roboto, &quot;Helvetica Neue&quot;, sans-serif;padding:0;vertical-align:top;text-align:left;padding-bottom:40px\">\r\n<div class=\"padding-content\" style=\"padding:0 40px\">\r\n<h2 class=\"heading\" style=\"font-weight:700;word-break:break-word;font-size:39px;line-height:44px\">\r\n2 unread messages since last Thursday\r\n</h2>\r\n<ul class=\"messages-summary\" style=\"font-size:18px;line-height:28px;margin:0 0 8px;padding:0 0 0 16px;margin:0;margin-bottom:32px\">\r\n<li>1 employer: iD Tech</li>\r\n<li>1 job in: Education</li>\r\n</ul>\r\n<div class=\"messages-container\">\r\n<div class=\"clickable-container\" style=\"border-radius:16px;border:1px solid #d4d6ec;background:#fff;padding:24px;margin-bottom:16px\">\r\n<a href=\"https://urldefense.proofpoint.com/v2/url?u=https-3A__email.notifications.joinhandshake.com_c_eJxkkEmO2zAQRU9DbgwZxUGkuOAiQMfXEKhiyWYsUQaHTnz7wEknyLAtfNR-5F-5F0UvozOWkxfWKHBageK0h7TN-2DWhpTRhaOvKcoiekyYHTA07TMmgIcVgmtINTAUww0awW-2Dc1rgGgXDavVwlnQqzB2wSk4MIjKOp68BDkKITRoOYI6R6uVnER0CBjtqJmGP7vr-2DcuR8i3kWG-5FhTmc8dr75W2uPytQnJi9MXvKz-5F59i8oJHfqdSf-5F5h6tLbPtejFySm3nouFOKc8nJ8m3eqNVxpfk2nwqR5RXeKqe9Mvf0w8nHEsD9Cumam3r4S3bfnHNOVamNSWeGEVkaO-5FF951oJ2aKcBJ6cH7aQeFnTrsEo5GbVaFTXwRzlixzYvHe-5FU-5FOf9sR1PKqdfjfXEpDktfbufPnArLz40Y0bxkvbsZ4qdN4-2DFQqM55UYlh-2D33uL94ea9UXmyjE2AmAfzdy-2D8BAAD-5F-5F-2Db7rXI&amp;d=DwMFaQ&amp;c=slrrB7dE8n7gBJbeO0g-IQ&amp;r=W4d5O1KeqHtZtS8Ifj-gIg&amp;m=Q7pIZx-6cQ6vyddP4tov8Ls2D1CYRZ5KpCVoAhq-ukTWHUhvBOSp2EGnmzkHupeZ&amp;s=olMuw0meYvMCM_yBLcqsen96hSxnFcxl-HodNeY3GOo&amp;e=\" style=\"color:#254fa5;font-weight:inherit;text-decoration:none;color:#000\">\r\n<div>\r\n<table class=\"message-container\" style=\"border-spacing:0;border-collapse:collapse;padding:0;vertical-align:top;text-align:left;width:100%\">\r\n<tr style=\"padding:0;vertical-align:top;text-align:left\">\r\n<td style=\"font-family:&quot;Suisse Int'l&quot;, -apple-system, BlinkMacSystemFont, &quot;Segoe UI&quot;, Roboto, &quot;Helvetica Neue&quot;, sans-serif;padding:0;vertical-align:top;text-align:left\">\r\n<table class=\"avatar_container\" style=\"border-spacing:0;border-collapse:collapse;padding:0;vertical-align:top;text-align:left;gap:10px;align-self:stretch\">\r\n<tr style=\"padding:0;vertical-align:top;text-align:left\">\r\n<td class=\"avatar_img\" rowspan=\"2\" style=\"font-family:&quot;Suisse Int'l&quot;, -apple-system, BlinkMacSystemFont, &quot;Segoe UI&quot;, Roboto, &quot;Helvetica Neue&quot;, sans-serif;padding:0;vertical-align:top;text-align:left;height:48px;width:48px\">\r\n<!--[if mso]><!-->\r\n<img alt=\"User photo\" class=\"user_photo\" src=\"https://handshake-production-cdn.joinhandshake.com/static_assets/default_user_3.png\" style=\"outline:none;text-decoration:none;-ms-interpolation-mode:bicubic;width:auto;max-width:100%;clear:both;display:block;border:none;width:48px;height:48px;border-radius:50%\">\r\n<!--<![endif]-->\r\n<!--[if mso]>\r\n<img alt='User photo' class='user_photo' height='48' src='https://handshake-production-cdn.joinhandshake.com/static_assets/default_user_3.png' style='width: 24px; height: 24px' width='48'>\r\n<![endif]-->\r\n</td>\r\n<td class=\"avatar_title\" style=\"font-family:&quot;Suisse Int'l&quot;, -apple-system, BlinkMacSystemFont, &quot;Segoe UI&quot;, Roboto, &quot;Helvetica Neue&quot;, sans-serif;padding:0;text-align:left;font-size:18px;line-height:27px;color:#1f202c;font-weight:bold;margin:0;padding-left:10px;vertical-align:top\">\r\nMaggie Wright\r\n</td>\r\n</tr>\r\n<tr style=\"padding:0;vertical-align:top;text-align:left\">\r\n<td class=\"avatar_subtitle\" style=\"font-family:&quot;Suisse Int'l&quot;, -apple-system, BlinkMacSystemFont, &quot;Segoe UI&quot;, Roboto, &quot;Helvetica Neue&quot;, sans-serif;padding:0;vertical-align:top;text-align:left;font-size:14px;line-height:20px;letter-spacing:-0.15px;color:#000;font-weight:400;margin:0;padding-left:10px\">\r\niD Tech 路 Regional Manager\r\n</td>\r\n</tr>\r\n</table>\r\n\r\n<div class=\"job-message-container\" style=\"margin-top:16px;width:100%;border-radius:16px;border:1px solid #d4d6ec\">\r\n<table class=\"job-details-table\" style=\"border-spacing:0;border-collapse:collapse;padding:0;vertical-align:top;text-align:left;margin:16px\">\r\n<tr style=\"padding:0;vertical-align:top;text-align:left\">\r\n<td style=\"font-family:&quot;Suisse Int'l&quot;, -apple-system, BlinkMacSystemFont, &quot;Segoe UI&quot;, Roboto, &quot;Helvetica Neue&quot;, sans-serif;padding:0;vertical-align:top;text-align:left\">\r\n<div class=\"job-name\" style=\"font-size:22px;font-weight:700;margin-bottom:16px\">Administrative Aide</div>\r\n</td>\r\n</tr>\r\n<tr style=\"padding:0;vertical-align:top;text-align:left\">\r\n<td style=\"font-family:&quot;Suisse Int'l&quot;, -apple-system, BlinkMacSystemFont, &quot;Segoe UI&quot;, Roboto, &quot;Helvetica Neue&quot;, sans-serif;padding:0;vertical-align:top;text-align:left\">\r\n<table class=\"job-details\" style=\"border-spacing:0;border-collapse:collapse;padding:0;vertical-align:top;text-align:left\">\r\n<tr style=\"padding:0;vertical-align:top;text-align:left\">\r\n<td style=\"font-family:&quot;Suisse Int'l&quot;, -apple-system, BlinkMacSystemFont, &quot;Segoe UI&quot;, Roboto, &quot;Helvetica Neue&quot;, sans-serif;padding:0;vertical-align:top;text-align:left\">\r\n<span class=\"job-detail\" style=\"white-space:nowrap;padding-right:12px\">\r\n<img alt=\"Location Icon\" height=\"24\" src=\"https://handshake-production-cdn.joinhandshake.com/static_assets/email_assets/icons/map-pin-icon.png\" width=\"24\" style=\"outline:none;text-decoration:none;-ms-interpolation-mode:bicubic;width:auto;max-width:100%;clear:both;display:block;border:none;width:24px;height:24px;padding-right:2px;display:inline-block;vertical-align:middle\">\r\n<span style=\"vertical-align:text-top\">Onsite</span>\r\n</span>\r\n<span class=\"job-detail\" style=\"white-space:nowrap;padding-right:12px\">\r\n<img alt=\"Job Type Icon\" height=\"24\" src=\"https://handshake-production-cdn.joinhandshake.com/static_assets/email_assets/icons/portfolio-icon.png\" width=\"24\" style=\"outline:none;text-decoration:none;-ms-interpolation-mode:bicubic;width:auto;max-width:100%;clear:both;display:block;border:none;width:24px;height:24px;padding-right:2px;display:inline-block;vertical-align:middle\">\r\n<span style=\"vertical-align:text-top\">Job</span>\r\n</span>\r\n</td>\r\n</tr>\r\n</table>\r\n</td>\r\n</tr>\r\n</table>\r\n</div>\r\n</td>\r\n</tr>\r\n</table>\r\n</div>\r\n</a>\r\n</div>\r\n</div>\r\n<div class=\"messages-container\">\r\n<div class=\"clickable-container\" style=\"border-radius:16px;border:1px solid #d4d6ec;background:#fff;padding:24px;margin-bottom:16px\">\r\n<a href=\"https://urldefense.proofpoint.com/v2/url?u=https-3A__email.notifications.joinhandshake.com_c_eJxkkEmO2zAQRU9DbgwZxUGkuOAiQMfXEKhiyWYsUQaHTnz7wEknyLAtfNR-5F-5F0UvozOWkxfWKHBageK0h7TN-2DWhpTRhaOvKcoiekyYHTA07TMmgIcVgmtINTAUww0awW-2Dc1rgGgXDavVwlnQqzB2wSk4MIjKOp68BDkKITRoOYI6R6uVnER0CBjtqJmGP7vr-2DcuR8i3kWG-5FhTmc8dr75W2uPytQnJi9MXvKz-5F59i8oJHfqdSf-5F5h6tLbPtejFySm3nouFOKc8nJ8m3eqNVxpfk2nwqR5RXeKqe9Mvf0w8nHEsD9Cumam3r4S3bfnHNOVamNSWeGEVkaO-5FF951oJ2aKcBJ6cH7aQeFnTrsEo5GbVaFTXwRzlixzYvHe-5FU-5FOf9sR1PKqdfjfXEpDktfbufPnArLz40Y0bxkvbsZ4qdN4-2DFQqM55UYlh-2D33uL94ea9UXmyjE2AmAfzdy-2D8BAAD-5F-5F-2Db7rXI&amp;d=DwMFaQ&amp;c=slrrB7dE8n7gBJbeO0g-IQ&amp;r=W4d5O1KeqHtZtS8Ifj-gIg&amp;m=Q7pIZx-6cQ6vyddP4tov8Ls2D1CYRZ5KpCVoAhq-ukTWHUhvBOSp2EGnmzkHupeZ&amp;s=olMuw0meYvMCM_yBLcqsen96hSxnFcxl-HodNeY3GOo&amp;e=\" style=\"color:#254fa5;font-weight:inherit;text-decoration:none;color:#000\">\r\n<div>\r\n<table class=\"message-container\" style=\"border-spacing:0;border-collapse:collapse;padding:0;vertical-align:top;text-align:left;width:100%\">\r\n<tr style=\"padding:0;vertical-align:top;text-align:left\">\r\n<td style=\"font-family:&quot;Suisse Int'l&quot;, -apple-system, BlinkMacSystemFont, &quot;Segoe UI&quot;, Roboto, &quot;Helvetica Neue&quot;, sans-serif;padding:0;vertical-align:top;text-align:left\">\r\n<table class=\"avatar_container\" style=\"border-spacing:0;border-collapse:collapse;padding:0;vertical-align:top;text-align:left;gap:10px;align-self:stretch\">\r\n<tr style=\"padding:0;vertical-align:top;text-align:left\">\r\n<td class=\"avatar_img\" rowspan=\"2\" style=\"font-family:&quot;Suisse Int'l&quot;, -apple-system, BlinkMacSystemFont, &quot;Segoe UI&quot;, Roboto, &quot;Helvetica Neue&quot;, sans-serif;padding:0;vertical-align:top;text-align:left;height:48px;width:48px\">\r\n<!--[if mso]><!-->\r\n<img alt=\"User photo\" class=\"user_photo\" src=\"https://handshake-production-cdn.joinhandshake.com/static_assets/default_user_3.png\" style=\"outline:none;text-decoration:none;-ms-interpolation-mode:bicubic;width:auto;max-width:100%;clear:both;display:block;border:none;width:48px;height:48px;border-radius:50%\">\r\n<!--<![endif]-->\r\n<!--[if mso]>\r\n<img alt='User photo' class='user_photo' height='48' src='https://handshake-production-cdn.joinhandshake.com/static_assets/default_user_3.png' style='width: 24px; height: 24px' width='48'>\r\n<![endif]-->\r\n</td>\r\n<td class=\"avatar_title\" style=\"font-family:&quot;Suisse Int'l&quot;, -apple-system, BlinkMacSystemFont, &quot;Segoe UI&quot;, Roboto, &quot;Helvetica Neue&quot;, sans-serif;padding:0;text-align:left;font-size:18px;line-height:27px;color:#1f202c;font-weight:bold;margin:0;padding-left:10px;vertical-align:top\">\r\nMaggie Wright\r\n</td>\r\n</tr>\r\n<tr style=\"padding:0;vertical-align:top;text-align:left\">\r\n<td class=\"avatar_subtitle\" style=\"font-family:&quot;Suisse Int'l&quot;, -apple-system, BlinkMacSystemFont, &quot;Segoe UI&quot;, Roboto, &quot;Helvetica Neue&quot;, sans-serif;padding:0;vertical-align:top;text-align:left;font-size:14px;line-height:20px;letter-spacing:-0.15px;color:#000;font-weight:400;margin:0;padding-left:10px\">\r\niD Tech 路 Regional Manager\r\n</td>\r\n</tr>\r\n</table>\r\n\r\n<div class=\"job-message-container\" style=\"margin-top:16px;width:100%;border-radius:16px;border:1px solid #d4d6ec\">\r\n<table class=\"job-details-table\" style=\"border-spacing:0;border-collapse:collapse;padding:0;vertical-align:top;text-align:left;margin:16px\">\r\n<tr style=\"padding:0;vertical-align:top;text-align:left\">\r\n<td style=\"font-family:&quot;Suisse Int'l&quot;, -apple-system, BlinkMacSystemFont, &quot;Segoe UI&quot;, Roboto, &quot;Helvetica Neue&quot;, sans-serif;padding:0;vertical-align:top;text-align:left\">\r\n<div class=\"job-name\" style=\"font-size:22px;font-weight:700;margin-bottom:16px\">Administrative Aide</div>\r\n</td>\r\n</tr>\r\n<tr style=\"padding:0;vertical-align:top;text-align:left\">\r\n<td style=\"font-family:&quot;Suisse Int'l&quot;, -apple-system, BlinkMacSystemFont, &quot;Segoe UI&quot;, Roboto, &quot;Helvetica Neue&quot;, sans-serif;padding:0;vertical-align:top;text-align:left\">\r\n<table class=\"job-details\" style=\"border-spacing:0;border-collapse:collapse;padding:0;vertical-align:top;text-align:left\">\r\n<tr style=\"padding:0;vertical-align:top;text-align:left\">\r\n<td style=\"font-family:&quot;Suisse Int'l&quot;, -apple-system, BlinkMacSystemFont, &quot;Segoe UI&quot;, Roboto, &quot;Helvetica Neue&quot;, sans-serif;padding:0;vertical-align:top;text-align:left\">\r\n<span class=\"job-detail\" style=\"white-space:nowrap;padding-right:12px\">\r\n<img alt=\"Location Icon\" height=\"24\" src=\"https://handshake-production-cdn.joinhandshake.com/static_assets/email_assets/icons/map-pin-icon.png\" width=\"24\" style=\"outline:none;text-decoration:none;-ms-interpolation-mode:bicubic;width:auto;max-width:100%;clear:both;display:block;border:none;width:24px;height:24px;padding-right:2px;display:inline-block;vertical-align:middle\">\r\n<span style=\"vertical-align:text-top\">Onsite</span>\r\n</span>\r\n<span class=\"job-detail\" style=\"white-space:nowrap;padding-right:12px\">\r\n<img alt=\"Job Type Icon\" height=\"24\" src=\"https://handshake-production-cdn.joinhandshake.com/static_assets/email_assets/icons/portfolio-icon.png\" width=\"24\" style=\"outline:none;text-decoration:none;-ms-interpolation-mode:bicubic;width:auto;max-width:100%;clear:both;display:block;border:none;width:24px;height:24px;padding-right:2px;display:inline-block;vertical-align:middle\">\r\n<span style=\"vertical-align:text-top\">Job</span>\r\n</span>\r\n</td>\r\n</tr>\r\n</table>\r\n</td>\r\n</tr>\r\n</table>\r\n</div>\r\n</td>\r\n</tr>\r\n</table>\r\n</div>\r\n</a>\r\n</div>\r\n</div>\r\n<table class=\"rebrand-cta\" style=\"border-spacing:0;border-collapse:collapse;padding:0;vertical-align:top;text-align:left;color:white;background-color:black;font-size:16px;border-radius:4px;height:40px;margin-top:24px\">\r\n<tr style=\"padding:0;vertical-align:top;text-align:left\">\r\n<td style=\"font-family:&quot;Suisse Int'l&quot;, -apple-system, BlinkMacSystemFont, &quot;Segoe UI&quot;, Roboto, &quot;Helvetica Neue&quot;, sans-serif;padding:0;vertical-align:top;text-align:left;padding:8px 16px;text-align:center;vertical-align:middle\">\r\n<a href=\"https://urldefense.proofpoint.com/v2/url?u=https-3A__email.notifications.joinhandshake.com_c_eJxkkMuu2yAURb8GJpEjOGAeAwaVbvMbFobjhMaGiMdt8-5FdV2tuqj-2DnR1tlrr-2DggWqUpOq6VYFYKJigePu1LLj1tKfieSl5SdBjQWGblFIxZJ8l8nFYT9GSFZ8qrqDYd6M15gXwGKzyAZpYLAQyZZ-5FM6r8GaCDQ5YDBzziWTMDNxjloKMDzawELUsySS-5Fdndzl9KyjefY7v5O55DOejubr0-5FGhGfCFwIXPJz-5FJ8icAklv2NtP-5F8QcRn9WFoZNSARbyNX9HFJeS3flgNb81dcXtOxElCv6IExjYOItx9GPo7BHw-2DfrpmIt6-2DI9-5F25xHTF1um-5FwrRm0gZtpmCsnKQFOa3BbtMGYJTYtIiS0UctcYS-2DrCPcsbvPx2MvT6ynXy3tRECd1rHfTx-2DIjVbnu1Izf4l6jjPGQbsLFX3HJeWONfv996C-5FGUfD-2DmKbLWfKcEbfHXwPAAD-5F-5F94uqvY&amp;d=DwMFaQ&amp;c=slrrB7dE8n7gBJbeO0g-IQ&amp;r=W4d5O1KeqHtZtS8Ifj-gIg&amp;m=Q7pIZx-6cQ6vyddP4tov8Ls2D1CYRZ5KpCVoAhq-ukTWHUhvBOSp2EGnmzkHupeZ&amp;s=ukplrn2qlR1NABVgYjtMMItjBeKNDNCpfLIQe01fdMs&amp;e=\" style=\"color:#254fa5;font-weight:inherit;text-decoration:none;color:white\">\r\n<span style=\"color: white;\">\r\nCatch up on messages\r\n</span>\r\n</a>\r\n</td>\r\n</tr>\r\n</table>\r\n\r\n<p class=\"want-daily-digest\" style=\"font-size:18px;line-height:28px;padding-top:20px\">\r\nWant daily digests? <a href=\"https://urldefense.proofpoint.com/v2/url?u=https-3A__email.notifications.joinhandshake.com_c_eJx0kc2u2yAQhZ8GNpEjDJifBYtKaV7DwsM4obGxxU-5FbvH3lq9zb21Zdgs6Zc-2Dab4HiwSlN0vVaCWSmYoLj6uIxpq3GO4Gvc0hiDQ0BjmZUdGDN1kvnQTQZ0Z4VnyqugZg307hgoo4eJh9mwyZjZIMfgBcyDnCx4T6PjjA9930sm-2DcDEOWgpuOmDBQZBD5JI9jm7nL9tMd19CuXuH3iGbaWLu9e6FyK-2DEH4l-5FJqe7V8V4ddWMBfCr4PtmTI9O6Sf19ozzpgxARYirr9fRFwgo684xlQxJ7-2DMK5bibzgGH5fnGOINSyVctbqOZWv5zdNSRh-5FGmKbt54fhgIn5JV0xxLYScXlj-5FPoEv-2D4-2D3hIRlx-2DIj4-5Fx9O8TaM2kBW06MFZ20nLZTWDnbubcKDFrESSje95CgzpODR5Y3dd1X7Yn5tN7SjkRrk5TWx6nV8VCs-5FNVqaE-5F0D-5FbGUOj1f2PwJ8dD8RHt3fE9LvjvwIAAP-5F-5FgufJ5w&amp;d=DwMFaQ&amp;c=slrrB7dE8n7gBJbeO0g-IQ&amp;r=W4d5O1KeqHtZtS8Ifj-gIg&amp;m=Q7pIZx-6cQ6vyddP4tov8Ls2D1CYRZ5KpCVoAhq-ukTWHUhvBOSp2EGnmzkHupeZ&amp;s=hyuMRkFZ0p93d2iGGM450ngo-7P0zJZZ0v8BFfzeh58&amp;e=\" style=\"color:#254fa5;font-weight:inherit;color:#5082ff;text-decoration:none\">Update your preferences</a>.\r\n</p>\r\n\r\n</div>\r\n</td>\r\n</tr>\r\n<tr style=\"padding:0;vertical-align:top;text-align:left\">\r\n<td style=\"font-family:&quot;Suisse Int'l&quot;, -apple-system, BlinkMacSystemFont, &quot;Segoe UI&quot;, Roboto, &quot;Helvetica Neue&quot;, sans-serif;padding:0;vertical-align:top;text-align:left\">\r\n<div class=\"rebrand-footer-background\" style=\"background-color:#f3f4fa;padding:40px 0;width:100%\">\r\n<div class=\"padding-content\" style=\"padding:0 40px\">\r\n<table class=\"rebrand-links\" style=\"border-spacing:0;border-collapse:collapse;padding:0;vertical-align:top;text-align:left;width:100%\">\r\n<tr style=\"padding:0;vertical-align:top;text-align:left\">\r\n<td class=\"rebrand-socials\" style=\"font-family:&quot;Suisse Int'l&quot;, -apple-system, BlinkMacSystemFont, &quot;Segoe UI&quot;, Roboto, &quot;Helvetica Neue&quot;, sans-serif;padding:0;vertical-align:top;text-align:left\">\r\n<table style=\"border-spacing:0;border-collapse:collapse;padding:0;vertical-align:top;text-align:left\">\r\n<tr style=\"padding:0;vertical-align:top;text-align:left\">\r\n<td style=\"font-family:&quot;Suisse Int'l&quot;, -apple-system, BlinkMacSystemFont, &quot;Segoe UI&quot;, Roboto, &quot;Helvetica Neue&quot;, sans-serif;padding:0;vertical-align:top;text-align:left\">\r\n<a href=\"https://urldefense.proofpoint.com/v2/url?u=https-3A__email.notifications.joinhandshake.com_c_eJxckM2u2yAQhZ8GNpEjDJifBYtKaV7Dwsw4oTE44qdp3r5ydVv13u3ojM53PnAcrNIU3aiVYFYKJigmH7c57y2uMfgW9zxHcBjQWGblEIxZBsk8DIsJerDCM-2DUVqFUHencgUI2ALCAzsILxkzRa-2D4kFPU1KKRodZ3wax1EyyScmzqCl4GYEG1gAPUki2f-5Fd9fxjj-5FnuM9S7f-2DA57Ilu7t7asxLxjfAr4dfX63WOuTZ-5FKz4dCcKvn76IuPaW5rr3EpCIS88FPcwxL-5FuvOWGt-5FobzMRsL4eqIJoTYExGXPzY-2DjsGnp4-2D3TMTlhfjY3jPEG9ZGv8rSmkkbtBmCsXKQlsthCXYdVs6NEqsWIBl9lh16aPPSwwOb-2D56e2-5F7GcvrbUk-2DEq9PSt8fpA7HS4nxTahoPSe9-2DRui0uVDQN5xjbliy3-5F4N-2DszYK5aDbbIjU2Zk9KfjvwMAAP-5F-5FBtOp7A&amp;d=DwMFaQ&amp;c=slrrB7dE8n7gBJbeO0g-IQ&amp;r=W4d5O1KeqHtZtS8Ifj-gIg&amp;m=Q7pIZx-6cQ6vyddP4tov8Ls2D1CYRZ5KpCVoAhq-ukTWHUhvBOSp2EGnmzkHupeZ&amp;s=FxtOWKBHmZmiwucQfM_qhYzW9wJC7DReOBWrwxOWPec&amp;e=\" style=\"color:#254fa5;font-weight:inherit\">\r\n<img alt=\"Instagram\" height=\"24\" src=\"https://handshake-production-cdn.joinhandshake.com/static_assets/email_assets/student_footer_v3_icons/instagram-lavender.png\" style=\"outline:none;text-decoration:none;-ms-interpolation-mode:bicubic;width:auto;max-width:100%;clear:both;display:block;border:none;width:24px;height:24px;padding:0 18px 0 0;width: 24px; height: 24px\" width=\"24\">\r\n</a>\r\n</td>\r\n<td style=\"font-family:&quot;Suisse Int'l&quot;, -apple-system, BlinkMacSystemFont, &quot;Segoe UI&quot;, Roboto, &quot;Helvetica Neue&quot;, sans-serif;padding:0;vertical-align:top;text-align:left\">\r\n<a href=\"https://urldefense.proofpoint.com/v2/url?u=https-3A__email.notifications.joinhandshake.com_c_eJxckEmO2zAURE9DbgwZn4M4LLgI4PgaAkV-2D2YwlyuCQtG8fKOgEcW8LBdSrFx2PVmmKjmklwEoBguLm0zrlvaUlBd-5FSnqcUHQY0FqwcgjHzIMHHYTZBD1Z4UF5FtehA744BxygkHxGjRGZGLqTyMygIowDtaXIc-2DMgYkyD5COIctRTcsGgDhKhHSST8v13PP-5FaU7z7HevcPPId9o6u7t-5FasRHwj-5FEr49eNICb-2D-2DNYm49rZNde8lIBGXngv6OKU87x-5FThrX6G07HVSyEq6O6YUx9I-2DLyx8BnGPz29OmWibj8QnysrymmG9ZGvwrSGqQN2gzBWDlIy-2DUwB7sMC-2DdGiUWLKIE-2Dyx57aNPcwwOb-2D7491-5F2F5fR3pZ4IV6e5r4-5FTJ2Klxfmm1MgOMa9-2Dxthpc6Ggbzil3LBkv-5F479M7YK5aDbbQMlGFAfzr-2DOwAA-5F-5F-2DPNaSH&amp;d=DwMFaQ&amp;c=slrrB7dE8n7gBJbeO0g-IQ&amp;r=W4d5O1KeqHtZtS8Ifj-gIg&amp;m=Q7pIZx-6cQ6vyddP4tov8Ls2D1CYRZ5KpCVoAhq-ukTWHUhvBOSp2EGnmzkHupeZ&amp;s=V1A8WLDwSFt4KV3Yu7xBazOobrlnPDvVv6cpyc7xxhI&amp;e=\" style=\"color:#254fa5;font-weight:inherit\">\r\n<img alt=\"X\" height=\"24\" src=\"https://handshake-production-cdn.joinhandshake.com/static_assets/email_assets/student_footer_v3_icons/x-lavender.png\" style=\"outline:none;text-decoration:none;-ms-interpolation-mode:bicubic;width:auto;max-width:100%;clear:both;display:block;border:none;width:24px;height:24px;padding:0 18px 0 0;width: 24px; height: 24px\" width=\"24\">\r\n</a>\r\n</td>\r\n<td style=\"font-family:&quot;Suisse Int'l&quot;, -apple-system, BlinkMacSystemFont, &quot;Segoe UI&quot;, Roboto, &quot;Helvetica Neue&quot;, sans-serif;padding:0;vertical-align:top;text-align:left\">\r\n<a href=\"https://urldefense.proofpoint.com/v2/url?u=https-3A__email.notifications.joinhandshake.com_c_eJxckMuu2yAURb8GJpEtDJjHgEGlNL9h4cMhoX5FPJrm7ytXt1XvnW442muv4HiwSlN0g1aCWSmYoLj5tE77UVNM4Gs69ikFh4DGMis7MGbuJPOhmw3ozgrPlFdBRQ304WyMNo4aox-2DZGGIQEYQZvQqcw6jETJPjjI-5FDMEgm-2DchEH7QU3AzBAoOgR0kk-2D7-2D79D-2DOtD-5F8HsrDL9jDsdHVPWp9FiK-2DEX4j-5FPZ6vfqalnos5-5FOZSfbpiohbq9tUjpYBibi2PaMPU9rn49e0YSn-2DjtM5GzPh6vy6YUhtI-2DL6x8ZHCH57-2DnTfibi-2DEJf1PYV0x1LpV1laM2lBmw6MlZ20XHYz2NhFzo0SUYsgGX3mIzSo09xgweq-2Db8-5F1eGO-2D-5FG0pF8LVZW7rcvlALDQ7X5Uah1PSu-5FUYGq0OMvqKU9or5t2v-5FwZ9ZmwF88k22oEpMzD60-5FHfAQAA-5F-5F-5FZG6mk&amp;d=DwMFaQ&amp;c=slrrB7dE8n7gBJbeO0g-IQ&amp;r=W4d5O1KeqHtZtS8Ifj-gIg&amp;m=Q7pIZx-6cQ6vyddP4tov8Ls2D1CYRZ5KpCVoAhq-ukTWHUhvBOSp2EGnmzkHupeZ&amp;s=Om9ENk-CPxjwhRDiYs4agadHaqzyY-9BXepEXW8Mano&amp;e=\" style=\"color:#254fa5;font-weight:inherit\">\r\n<img alt=\"TikTok\" height=\"24\" src=\"https://handshake-production-cdn.joinhandshake.com/static_assets/email_assets/student_footer_v3_icons/tiktok-lavender.png\" style=\"outline:none;text-decoration:none;-ms-interpolation-mode:bicubic;width:auto;max-width:100%;clear:both;display:block;border:none;width:24px;height:24px;padding:0 18px 0 0;width: 24px; height: 24px\" width=\"24\">\r\n</a>\r\n</td>\r\n</tr>\r\n</table>\r\n</td>\r\n<td class=\"rebrand-app-store\" style=\"font-family:&quot;Suisse Int'l&quot;, -apple-system, BlinkMacSystemFont, &quot;Segoe UI&quot;, Roboto, &quot;Helvetica Neue&quot;, sans-serif;padding:0;vertical-align:top;text-align:left\">\r\n<table style=\"border-spacing:0;border-collapse:collapse;padding:0;vertical-align:top;text-align:left;margin-right:0;margin-left:auto\">\r\n<tr style=\"padding:0;vertical-align:top;text-align:left\">\r\n<td style=\"font-family:&quot;Suisse Int'l&quot;, -apple-system, BlinkMacSystemFont, &quot;Segoe UI&quot;, Roboto, &quot;Helvetica Neue&quot;, sans-serif;padding:0;vertical-align:top;text-align:left\">\r\n<a style=\"color:#254fa5;font-weight:inherit;color: inherit; text-decoration: none;\" href=\"https://urldefense.proofpoint.com/v2/url?u=https-3A__email.notifications.joinhandshake.com_c_eJxkkMvO2yAQhZ8GNpEjDJjLgkWl1K-2DBMDNOqG1sGWibt69c-5Fa162Y7O6HznA8fBKk3R9VoJZqVgguIW0urzXtOcYqhpzz6Bw4jGMiu7aMzUSRagm0zUnRWBqaBAzTrSl-2DOWTVIELSBqZFZPnOEkQKo5GKZB0eQ440Pf95JJPjBxBy0FNz3YyCLoQRLJ-5Fuwu9y97yq-2DQobzCgve4b3R1r1qPQsQnwkfCx-5Fxu-5F6cIH1Oe9pbBrykvhfAxHIdPudSwrkSMrW6-2D7O2MSMSj5RMD-2DOvju9-2DwlPBEf4nAk3B1RTeE1DYiHj-5F9fBxj2I6QnpmIxzfEZX17SE8slf6rT2smbdSmi8bKTlouuynauZs5N0rMWoBk9Dh3aLH6qcUFq-5Fu8Hev-2DxvP2q6XcCFe3qa3L7QOx0NOFqtTQX9re7Y7QaHXxxFDRp1zxzGH9PehvxlbwvNgG2zNleka-5FOv4jAAD-5F-5F576sLA&amp;d=DwMFaQ&amp;c=slrrB7dE8n7gBJbeO0g-IQ&amp;r=W4d5O1KeqHtZtS8Ifj-gIg&amp;m=Q7pIZx-6cQ6vyddP4tov8Ls2D1CYRZ5KpCVoAhq-ukTWHUhvBOSp2EGnmzkHupeZ&amp;s=-y8KOSF3gWvzaAYP8NcCnnIeGDrSYTth3XP3m2ccqEg&amp;e=\"><img alt=\"Apple App Store\" height=\"26\" src=\"https://handshake-production-cdn.joinhandshake.com/static_assets/email_assets/student_footer_v3_icons/apple-app-store.png\" style=\"outline:none;text-decoration:none;-ms-interpolation-mode:bicubic;width:auto;max-width:100%;clear:both;display:block;border:none;height:26px;padding:0 0 0 16px\">\r\n</a>\r\n</td>\r\n<td style=\"font-family:&quot;Suisse Int'l&quot;, -apple-system, BlinkMacSystemFont, &quot;Segoe UI&quot;, Roboto, &quot;Helvetica Neue&quot;, sans-serif;padding:0;vertical-align:top;text-align:left\">\r\n<a style=\"color:#254fa5;font-weight:inherit;color: inherit; text-decoration: none;\" href=\"https://urldefense.proofpoint.com/v2/url?u=https-3A__email.notifications.joinhandshake.com_c_eJxkkMvO2yAQhZ8GNpEjDJjLgkWl1K-2DBMDNOqG1sGWibt69c-5Fa162Y7O6HznA8fBKk3R9VoJZqVgguIW0urzXtOcYqhpzz6Bw4jGMiu7aMzUSRagm0zUnRWBqaBAzTrSl-2DOWTVIELSBqZFZPnOEkQKo5GKZB0eQ440Pf95JJPjBxBy0FNz3YyCLoQRLJ-5Fuwu9y97yq-2DQobzCgve4b3R1r1qPQsQnwkfCx-5Fxu-5F6cIH1Oe9pbBrykvhfAxHIdPudSwrkSMrW6-2D7O2MSMSj5RMD-2DOvju9-2DwlPBEf4nAk3B1RTeE1DYiHj-5F9fBxj2I6QnpmIxzfEZX17SE8slf6rT2smbdSmi8bKTlouuynauZs5N0rMWoBk9Dh3aLH6qcUFq-5Fu8Hev-2DxvP2q6XcCFe3qa3L7QOx0NOFqtTQX9re7Y7QaHXxxFDRp1zxzGH9PehvxlbwvNgG2zNleka-5FOv4jAAD-5F-5F576sLA&amp;d=DwMFaQ&amp;c=slrrB7dE8n7gBJbeO0g-IQ&amp;r=W4d5O1KeqHtZtS8Ifj-gIg&amp;m=Q7pIZx-6cQ6vyddP4tov8Ls2D1CYRZ5KpCVoAhq-ukTWHUhvBOSp2EGnmzkHupeZ&amp;s=-y8KOSF3gWvzaAYP8NcCnnIeGDrSYTth3XP3m2ccqEg&amp;e=\"><img alt=\"Google Play Store\" height=\"26\" src=\"https://handshake-production-cdn.joinhandshake.com/static_assets/email_assets/student_footer_v3_icons/google-play-store.png\" style=\"outline:none;text-decoration:none;-ms-interpolation-mode:bicubic;width:auto;max-width:100%;clear:both;display:block;border:none;height:26px;padding:0 0 0 16px\">\r\n</a>\r\n</td>\r\n</tr>\r\n</table>\r\n</td>\r\n</tr>\r\n</table>\r\n<div class=\"rebrand-footer-container\" style=\"margin-top:14px\">\r\n<p class=\"rebrand-footer-text\" style=\"font-size:18px;line-height:28px;color:#878aae;font-size:14px;line-height:125%;margin:0 0 20px\">\r\nIf you'd no longer like to receive emails like this you can <a href=\"https://urldefense.proofpoint.com/v2/url?u=https-3A__email.notifications.joinhandshake.com_c_eJyMkc2u2yAQhZ8GNpGjMWB-2DFiwqpXkNC8OQ0Ng44qdt3r7KVW57227uEnTOnDPfBMuCkYqiHZXkYAQHTnFzaZ3z3lJM3rW05zkFix61ASMGr-5FUyCHBhWLRXg-2DEOpJNBRuXp1UYXEcCwqIBFwAUEj47pyJZJGYhAk2XApnEcBQg2AT8GJTjTYzAefFCTIAI-2DZtfjtz3lq8uhXt0Nj37f6Gqvrd0r4V8IOxN2zo-5F-2Dv4qwc69YKmHnyYwg9QhP6ce17gUjFsweK-2DHnPy-5FCT76gazin3LBkt84b1uouOP9AvK2POaQL1kaY7G2b697Lm6nngi7MKS-5F7z9-2DOJ00sL-2DmGIfWN8NMb5Nend9vdpUsm-5FPTXePrvDZQCYbzSg9dGDMIwMSzexCEypiWPigcB9F720H2bl-2D5v2OzX7b7uDyyH95R6IEwelr7eDq-2DKlRbrmpTT-2DGT-5F6EcMnTb7KQT0yfjZ7Z0x-5FW7ZrwAAAP-5F-5FQ63Jwg&amp;d=DwMFaQ&amp;c=slrrB7dE8n7gBJbeO0g-IQ&amp;r=W4d5O1KeqHtZtS8Ifj-gIg&amp;m=Q7pIZx-6cQ6vyddP4tov8Ls2D1CYRZ5KpCVoAhq-ukTWHUhvBOSp2EGnmzkHupeZ&amp;s=n-GN6q7QKwZCSpMQKEG91jOjMxpnGVk009eiJUQsmdU&amp;e=\" style=\"color:#254fa5;font-weight:inherit;color:inherit\">sign in</a> to manage your notification preferences or <a href=\"https://urldefense.proofpoint.com/v2/url?u=https-3A__email.notifications.joinhandshake.com_u_eJxczk1uwyAQQOHThI2FNWDMz4Jlz2HBMCTUNo4MbpXbV5G6qLp-5F0vuSl8lpw2gPZVvq0UsuGHo56lKSJyTrwCmO1kauICQeLRrupgA66KSzQfbwmEN0maSbURtwIDKCiG4C0jpaIVnxEuQshFCg5AzTmIyapBXJIWAys7op-2DPtu4-2DdR6iPU1B5hpRGPnf23GQPKobEcrVNcOal4RJd5ltLqKZspKWDP80gX9iVeuFL3H-5FtzO150Dhj2Zyj32oab1EO8tnXYqbVwp8ZOH7rWs3ibXtdI6WLd40mh01Jqp7OGbfmtl2-2DidXstqdypdXY1Ot-2D22QnQVgD78vInAAD-5F-5FzCwcfM&amp;d=DwMFaQ&amp;c=slrrB7dE8n7gBJbeO0g-IQ&amp;r=W4d5O1KeqHtZtS8Ifj-gIg&amp;m=Q7pIZx-6cQ6vyddP4tov8Ls2D1CYRZ5KpCVoAhq-ukTWHUhvBOSp2EGnmzkHupeZ&amp;s=D00u3hBZVknk3jIUbJG2-8GJ2gC_JBXg2WGF8H_x3iw&amp;e=\" style=\"color:#254fa5;font-weight:inherit;color:inherit\">unsubscribe</a>.\r\n</p>\r\n<p class=\"rebrand-footer-text address\" style=\"font-size:18px;line-height:28px;color:#878aae;margin:0 0 20px;font-size:14px;line-height:125%;font-weight:bold\">P.O. Box 40770, San Francisco, CA 94140</p>\r\n<img alt=\"Handshake\" class=\"handshake-logo\" height=\"30\" src=\"https://handshake-production-cdn.joinhandshake.com/static_assets/handshake_logo_neutral.png\" style=\"outline:none;text-decoration:none;-ms-interpolation-mode:bicubic;width:auto;max-width:100%;clear:both;display:block;width: 150px; height: 30px\" title=\"Handshake\" width=\"150\">\r\n</div>\r\n</div>\r\n</div>\r\n\r\n</td>\r\n</tr>\r\n</table>\r\n<img width=\"1\" height=\"1\" alt=\"\" src=\"https://email.notifications.joinhandshake.com/o/eJxczksO2yAQgOHThI2FNcDwWrDsOSw8jBPqV2Rwq9y-itRF1f0v_V9JukTnBSflnYGIBozgPddtOs5el0q51_OYaklMHCJElBTCLBFykXMgL6PJ4LIrbvEkXon14rUNqKydQ_AABARKaUCHVs1F1KRBW6UUAmoLZiwejQ6qRAIq3uID4d93G3-e9Xjlo7RXXnmkcxf_27wHjOSDpBBRYtQoZ4qLXLQOzizeFATxvs5yU5_mm1bu6cf-3s4PXwPl_Z3r82jDQ7thvrd12Lm1_OQmrpS7c1Z9TZ975HKLnuji3HmqR-fryNv0t55-M6_bZyr1ya2Lu_H1tdmowAUF4lfSfwIAAP__EGBzvg\"></body>\r\n</html>"
}